shell_logger/__init__.py
shell_logger/html_utilities.py
shell_logger/py.typed
shell_logger/resources/Chart.bundle.min.js
shell_logger/resources/Chart.min.css
shell_logger/resources/bootstrap.bundle.min.js
shell_logger/resources/bootstrap.min.css
shell_logger/resources/child_logger_style.css
shell_logger/resources/code_block_style.css
shell_logger/resources/command_style.css
shell_logger/resources/detail_list_style.css
shell_logger/resources/diagnostics_style.css
shell_logger/resources/jquery.slim.min.js
shell_logger/resources/message_style.css
shell_logger/resources/output_style.css
shell_logger/resources/parent_logger_style.css
shell_logger/resources/search_controls.css
shell_logger/resources/search_icon.svg
shell_logger/resources/search_output.js
shell_logger/resources/templates/child_logger.html
shell_logger/resources/templates/command.html
shell_logger/resources/templates/command_detail.html
shell_logger/resources/templates/command_detail_list.html
shell_logger/resources/templates/diagnostics.html
shell_logger/resources/templates/hidden_command_detail.html
shell_logger/resources/templates/html_message.html
shell_logger/resources/templates/message.html
shell_logger/resources/templates/output_block.html
shell_logger/resources/templates/output_card.html
shell_logger/resources/templates/output_card_collapsed.html
shell_logger/resources/templates/output_line.html
shell_logger/resources/templates/parent_logger.html
shell_logger/resources/templates/stat_chart.html
shell_logger/resources/top_level_style_adjustments.css
shell_logger/shell.py
shell_logger/shell_logger.py
shell_logger/stats_collector.py
shell_logger/trace_collector.py
shell_logger_sandialabs-3.0.4.dist-info/METADATA
shell_logger_sandialabs-3.0.4.dist-info/WHEEL
shell_logger_sandialabs-3.0.4.dist-info/licenses/LICENSE.md
shell_logger_sandialabs-3.0.4.dist-info/RECORD
