Metadata-Version: 2.4
Name: shell-logger-sandialabs
Version: 3.0.4
Summary: A tool for keeping track of Python's interactions with the shell.
License: LICENSE.md
License-File: LICENSE.md
Keywords: shell,logging
Author: Josh Braun
Author-email: josbrau@sandia.gov
Requires-Python: >=3.10
Classifier: Development Status :: 3 - Alpha
Classifier: Intended Audience :: Developers
Classifier: Intended Audience :: Information Technology
Classifier: Intended Audience :: System Administrators
Classifier: License :: OSI Approved :: BSD License
Classifier: License :: Other/Proprietary License
Classifier: Natural Language :: English
Classifier: Operating System :: MacOS
Classifier: Operating System :: POSIX
Classifier: Programming Language :: Python :: 3
Classifier: Programming Language :: Python :: 3.10
Classifier: Programming Language :: Python :: 3.11
Classifier: Programming Language :: Python :: 3.12
Classifier: Programming Language :: Python :: 3.13
Classifier: Programming Language :: Python :: 3.14
Classifier: Programming Language :: Python :: 3 :: Only
Classifier: Topic :: Software Development
Classifier: Topic :: Software Development :: Debuggers
Classifier: Topic :: Software Development :: Documentation
Classifier: Topic :: System :: Logging
Classifier: Topic :: System :: Shells
Classifier: Topic :: System :: System Shells
Classifier: Typing :: Typed
Project-URL: CI, https://github.com/sandialabs/shell-logger/actions
Project-URL: Documentation, https://shell-logger.readthedocs.io
Project-URL: Issues, https://github.com/sandialabs/shell-logger/issues
Project-URL: Repository, https://github.com/sandialabs/shell-logger
